CHANGELOG.md
ukedown/__init__.py
ukedown/patterns.py
ukedown/translations.py
ukedown/udn.py
ukedown-2.2.2.dist-info/LICENSE.txt
ukedown-2.2.2.dist-info/METADATA
ukedown-2.2.2.dist-info/WHEEL
ukedown-2.2.2.dist-info/RECORD
