Metadata-Version: 2.1
Name: ukedown
Version: 2.2.2
Summary: Markdown extensions for songsheet creation
Home-page: https://github.com/lanky/ukedown
License: GPL-3.0-or-later
Author: Stuart Sears
Author-email: stuart@sjsears.com
Requires-Python: >=3.9
Classifier: License :: OSI Approved :: GNU General Public License v3 or later (GPLv3+)
Classifier: Programming Language :: Python :: 3
Classifier: Programming Language :: Python :: 3.9
Classifier: Programming Language :: Python :: 3.10
Classifier: Programming Language :: Python :: 3.11
Requires-Dist: markdown (>=3.5.2,<4.0.0)
Project-URL: Bug Tracker, https://github.com/lanky/ukedown/issues
Project-URL: Repository, https://github.com/lanky/ukedown
